reposter/__main__.py
reposter/autotests/msgs.py
reposter/autotests/pyright.py
reposter/autotests/restricted.py
reposter/autotests/ruff.py
reposter/autotests/run.py
reposter/autotests/timer.py
reposter/autotests/unrestricted.py
reposter/core/common.py
reposter/core/config.py
reposter/core/types.py
reposter/db/init.py
reposter/db/models.py
reposter/funcs/handle.py
reposter/funcs/logging.py
reposter/funcs/other.py
reposter/funcs/parse_conf.py
reposter/funcs/status.py
reposter/funcs/suppress.py
reposter/handlers/edit.py
reposter/handlers/forward_unrestricted.py
reposter/handlers/on_msg.py
reposter/handlers/other.py
reposter/handlers/resend_restricted.py
reposter/handlers/service.py
reposter/handlers/set.py
reposter/handlers/stream_notify.py
reposter/shortshot/shortshot.py
reposter/tg/chunk_gen.py
reposter/tg/history.py
reposter/tg/restricted.py
reposter/tg/save_file.py
reposter-25.1.0.dist-info/METADATA
reposter-25.1.0.dist-info/WHEEL
reposter-25.1.0.dist-info/entry_points.txt
reposter-25.1.0.dist-info/top_level.txt
reposter-25.1.0.dist-info/RECORD
