Metadata-Version: 2.4
Name: reposter
Version: 25.1.0
Summary: userbot that forwards messages from telegram channels to others in real time
Project-URL: repo, https://github.com/gmankab/reposter
Classifier: License :: OSI Approved :: GNU Affero General Public License v3
Requires-Python: >=3.11
Requires-Dist: tortoise-orm
Requires-Dist: tgcrypto-pyrofork
Requires-Dist: pyrofork
Requires-Dist: rich
Provides-Extra: tests
Requires-Dist: pyright; extra == "tests"
Requires-Dist: ruff; extra == "tests"
Provides-Extra: build
Requires-Dist: setuptools; extra == "build"
Requires-Dist: twine; extra == "build"
Requires-Dist: build; extra == "build"
